{
    "url": "https://mangatale.co/the-man-chapter-183/",
    "images": [
        "https://cdn.uqni.net/images/16/the-man/183/00.jpg",
        "https://cdn.uqni.net/images/16/the-man/183/01.jpg",
        "https://cdn.uqni.net/images/16/the-man/183/02.jpg",
        "https://cdn.uqni.net/images/16/the-man/183/03.jpg",
        "https://cdn.uqni.net/images/16/the-man/183/04.jpg",
        "https://cdn.uqni.net/images/16/the-man/183/05.jpg",
        "https://cdn.uqni.net/images/16/the-man/183/06.jpg",
        "https://cdn.uqni.net/images/16/the-man/183/07.jpg",
        "https://cdn.uqni.net/images/16/the-man/183/08.jpg",
        "https://cdn.uqni.net/images/16/the-man/183/09.jpg",
        "https://cdn.uqni.net/images/16/the-man/183/10.jpg",
        "https://cdn.uqni.net/images/16/the-man/183/11.jpg",
        "https://cdn.uqni.net/images/16/the-man/183/12.jpg",
        "https://cdn.uqni.net/images/16/the-man/183/13.jpg",
        "https://cdn.uqni.net/images/16/the-man/183/14.jpg",
        "https://cdn.uqni.net/images/16/the-man/183/15.jpg",
        "https://cdn.uqni.net/images/16/the-man/183/16.jpg",
        "https://cdn.uqni.net/images/16/the-man/183/17.jpg",
        "https://cdn.uqni.net/images/16/the-man/183/18.jpg",
        "https://cdn.uqni.net/images/16/the-man/183/19.jpg"
    ],
    "idle": "5",
    "disqus_sn": "baca-manga-4",
    "disqus_id": "514820 https://mangatale.co/?p=514820"
}