{
    "url": "https://kiryuu.id/how-to-live-as-a-villain-chapter-9/",
    "images": [
        "https://v2.yuucdn.net/wp-content/uploads/H/How%20to%20Live%20as%20a%20Villain/Chapter%2009/000.jpg",
        "https://v2.yuucdn.net/wp-content/uploads/H/How%20to%20Live%20as%20a%20Villain/Chapter%2009/001.jpg",
        "https://v2.yuucdn.net/wp-content/uploads/H/How%20to%20Live%20as%20a%20Villain/Chapter%2009/002.jpg",
        "https://v2.yuucdn.net/wp-content/uploads/H/How%20to%20Live%20as%20a%20Villain/Chapter%2009/003.jpg",
        "https://v2.yuucdn.net/wp-content/uploads/H/How%20to%20Live%20as%20a%20Villain/Chapter%2009/004.jpg",
        "https://v2.yuucdn.net/wp-content/uploads/H/How%20to%20Live%20as%20a%20Villain/Chapter%2009/005.jpg",
        "https://v2.yuucdn.net/wp-content/uploads/H/How%20to%20Live%20as%20a%20Villain/Chapter%2009/006.jpg",
        "https://v2.yuucdn.net/wp-content/uploads/H/How%20to%20Live%20as%20a%20Villain/Chapter%2009/007.jpg",
        "https://v2.yuucdn.net/wp-content/uploads/H/How%20to%20Live%20as%20a%20Villain/Chapter%2009/008.jpg",
        "https://v2.yuucdn.net/wp-content/uploads/H/How%20to%20Live%20as%20a%20Villain/Chapter%2009/009.jpg",
        "https://v2.yuucdn.net/wp-content/uploads/H/How%20to%20Live%20as%20a%20Villain/Chapter%2009/010.jpg",
        "https://v2.yuucdn.net/wp-content/uploads/H/How%20to%20Live%20as%20a%20Villain/Chapter%2009/011.jpg",
        "https://v2.yuucdn.net/wp-content/uploads/H/How%20to%20Live%20as%20a%20Villain/Chapter%2009/012.jpg",
        "https://v2.yuucdn.net/wp-content/uploads/H/How%20to%20Live%20as%20a%20Villain/Chapter%2009/013.jpg",
        "https://v2.yuucdn.net/wp-content/uploads/H/How%20to%20Live%20as%20a%20Villain/Chapter%2009/014.jpg",
        "https://v2.yuucdn.net/wp-content/uploads/H/How%20to%20Live%20as%20a%20Villain/Chapter%2009/015.jpg",
        "https://v2.yuucdn.net/wp-content/uploads/H/How%20to%20Live%20as%20a%20Villain/Chapter%2009/016.jpg",
        "https://v2.yuucdn.net/wp-content/uploads/H/How%20to%20Live%20as%20a%20Villain/Chapter%2009/017.jpg",
        "https://v2.yuucdn.net/wp-content/uploads/H/How%20to%20Live%20as%20a%20Villain/Chapter%2009/018.jpg",
        "https://v2.yuucdn.net/wp-content/uploads/H/How%20to%20Live%20as%20a%20Villain/Chapter%2009/019.jpg",
        "https://v2.yuucdn.net/wp-content/uploads/H/How%20to%20Live%20as%20a%20Villain/Chapter%2009/020.jpg",
        "https://v2.yuucdn.net/wp-content/uploads/H/How%20to%20Live%20as%20a%20Villain/Chapter%2009/021.jpg",
        "https://v2.yuucdn.net/wp-content/uploads/H/How%20to%20Live%20as%20a%20Villain/Chapter%2009/022.jpg",
        "https://v2.yuucdn.net/wp-content/uploads/H/How%20to%20Live%20as%20a%20Villain/Chapter%2009/023.jpg",
        "https://v2.yuucdn.net/wp-content/uploads/H/How%20to%20Live%20as%20a%20Villain/Chapter%2009/024.jpg",
        "https://v2.yuucdn.net/wp-content/uploads/H/How%20to%20Live%20as%20a%20Villain/Chapter%2009/025.jpg",
        "https://v2.yuucdn.net/wp-content/uploads/H/How%20to%20Live%20as%20a%20Villain/Chapter%2009/026.jpg",
        "https://v2.yuucdn.net/wp-content/uploads/H/How%20to%20Live%20as%20a%20Villain/Chapter%2009/027.jpg"
    ],
    "idle": "5",
    "disqus_sn": "kiryuu-id",
    "disqus_id": "327790 http://kiryuu.id/?p=327790"
}